pfin/__init__.py
pfin-0.0.1.dist-info/LICENSE
pfin-0.0.1.dist-info/WHEEL
pfin-0.0.1.dist-info/METADATA
pfin-0.0.1.dist-info/RECORD
